botnoinlp/__init__.py
botnoinlp/botnoi.py
botnoinlp-0.0.7.dist-info/LICENSE.txt
botnoinlp-0.0.7.dist-info/METADATA
botnoinlp-0.0.7.dist-info/WHEEL
botnoinlp-0.0.7.dist-info/top_level.txt
botnoinlp-0.0.7.dist-info/RECORD
