Metadata-Version: 2.1
Name: botnoinlp
Version: 0.0.7
Summary: APIs to access BOTNOI openapi
Home-page: https://github.com/winn/botnoi
Author: Winn Voravuthikunchai
Author-email: vwinnv@gmail.com
License: MIT
Download-URL: https://pypi.org/project/botnoinlp/
Keywords: NLP
Platform: UNKNOWN
